anyway/sdk/__init__.py
anyway/sdk/annotation/__init__.py
anyway/sdk/annotation/base_annotation.py
anyway/sdk/annotation/user_feedback.py
anyway/sdk/associations/__init__.py
anyway/sdk/associations/associations.py
anyway/sdk/client/__init__.py
anyway/sdk/client/client.py
anyway/sdk/client/http.py
anyway/sdk/config/__init__.py
anyway/sdk/datasets/__init__.py
anyway/sdk/datasets/attachment.py
anyway/sdk/datasets/base.py
anyway/sdk/datasets/column.py
anyway/sdk/datasets/dataset.py
anyway/sdk/datasets/datasets.py
anyway/sdk/datasets/model.py
anyway/sdk/datasets/row.py
anyway/sdk/decorators/__init__.py
anyway/sdk/decorators/base.py
anyway/sdk/evaluator/__init__.py
anyway/sdk/evaluator/config.py
anyway/sdk/evaluator/evaluator.py
anyway/sdk/evaluator/evaluators_made_by_traceloop.py
anyway/sdk/evaluator/field_mapping.py
anyway/sdk/evaluator/model.py
anyway/sdk/evaluator/stream_client.py
anyway/sdk/experiment/__init__.py
anyway/sdk/experiment/experiment.py
anyway/sdk/experiment/model.py
anyway/sdk/experiment/utils.py
anyway/sdk/fetcher.py
anyway/sdk/generated/__init__.py
anyway/sdk/generated/evaluators/__init__.py
anyway/sdk/generated/evaluators/registry.py
anyway/sdk/generated/evaluators/request.py
anyway/sdk/generated/evaluators/response.py
anyway/sdk/guardrails/__init__.py
anyway/sdk/guardrails/guardrails.py
anyway/sdk/guardrails/types.py
anyway/sdk/images/image_uploader.py
anyway/sdk/instruments.py
anyway/sdk/logging/__init__.py
anyway/sdk/logging/logging.py
anyway/sdk/metrics/__init__.py
anyway/sdk/metrics/metrics.py
anyway/sdk/prompts/__init__.py
anyway/sdk/prompts/client.py
anyway/sdk/prompts/model.py
anyway/sdk/prompts/registry.py
anyway/sdk/py.typed
anyway/sdk/tracing/__init__.py
anyway/sdk/tracing/content_allow_list.py
anyway/sdk/tracing/context_manager.py
anyway/sdk/tracing/manual.py
anyway/sdk/tracing/tracing.py
anyway/sdk/utils/__init__.py
anyway/sdk/utils/in_memory_span_exporter.py
anyway/sdk/utils/json_encoder.py
anyway/sdk/utils/package_check.py
anyway_sdk-0.0.4.dist-info/METADATA
anyway_sdk-0.0.4.dist-info/WHEEL
anyway_sdk-0.0.4.dist-info/RECORD
